README.md
setup.py
chimas.egg-info/PKG-INFO
chimas.egg-info/SOURCES.txt
chimas.egg-info/dependency_links.txt
chimas.egg-info/top_level.txt
pybomberman/__init__.py
pybomberman/bomb.py
pybomberman/bomber_and_player.py
pybomberman/exception.py
pybomberman/map.py
pybomberman/powerup.py
pybomberman/server.py
pybomberman/session_and_game.py