Metadata-Version: 2.1
Name: chimas
Version: 0.0.1
Summary: Discussion Forum API
Home-page: https://github.com/TryChimas/chimas
Author: chimas Staff
Author-email: kassivs+chimas@gmail.com
License: UNKNOWN
Platform: UNKNOWN
Classifier: Programming Language :: Python :: 3
Classifier: License :: OSI Approved :: MIT License
Classifier: Operating System :: OS Independent
Requires-Python: >=3.6
